lwk/__init__.py
lwk/lwk/__init__.py
lwk/lwk/liblwk.so
lwk/lwk/lwk.py
lwk-0.14.0.dist-info/METADATA
lwk-0.14.0.dist-info/WHEEL
lwk-0.14.0.dist-info/RECORD
