Metadata-Version: 2.4
Name: lwk
Version: 0.14.0
Summary: Liquid Wallet Kit
Keywords: liquid,elements,wallet
Project-URL: documentation, https://docs.rs/lwk_bindings/latest/lwk_bindings/
Project-URL: homepage, https://github.com/blockstream/lwk
